azure_odbc_client/__init__.py
azure_odbc_client/client.py
azure_odbc_client/exceptions.py
tests/__init__.py
tests/test_client.py
tests/test_exceptions.py
azure_odbc_client-1.0.0.dist-info/LICENSE
azure_odbc_client-1.0.0.dist-info/METADATA
azure_odbc_client-1.0.0.dist-info/WHEEL
azure_odbc_client-1.0.0.dist-info/top_level.txt
azure_odbc_client-1.0.0.dist-info/RECORD
