Metadata-Version: 2.1
Name: azure-odbc-client
Version: 1.0.0
Summary: 一个简单易用的Azure SQL Server ODBC客户端包
Home-page: https://github.com/yourusername/azure-odbc-client
Author: Your Name
Author-email: your.email@example.com
Keywords: azure sql server odbc database client
Classifier: Development Status :: 4 - Beta
Classifier: Intended Audience :: Developers
Classifier: Operating System :: OS Independent
Classifier: Programming Language :: Python :: 3
Classifier: Programming Language :: Python :: 3.7
Classifier: Programming Language :: Python :: 3.8
Classifier: Programming Language :: Python :: 3.9
Classifier: Programming Language :: Python :: 3.10
Classifier: Programming Language :: Python :: 3.11
Classifier: Topic :: Database
Classifier: Topic :: Software Development :: Libraries :: Python Modules
Requires-Python: >=3.7
License-File: LICENSE
Requires-Dist: pyodbc>=4.0.30
